phrenktest/__init__.py
phrenktest/hello.py
phrenktest/__pycache__/__init__.cpython-39.pyc
phrenktest/__pycache__/hello.cpython-39.pyc
phrenktest/othermodule/__init__.py
phrenktest/othermodule/hello2.py
phrenk10_meganew-0.1.6.dist-info/METADATA
phrenk10_meganew-0.1.6.dist-info/WHEEL
phrenk10_meganew-0.1.6.dist-info/top_level.txt
phrenk10_meganew-0.1.6.dist-info/RECORD
