Metadata-Version: 2.1
Name: phrenk10-meganew
Version: 0.1.6
Summary: testest
Author: test
